License
MANIFEST.in
README.rst
requirements.txt
setup.py
bin/htk_io_get_label_map_leaf_macro_id_to_leaf_index.py
bin/htk_io_map_alignment_files.py
bin/htk_io_map_alignment_files_label_sublabel_to_leaf_macro_id.py
example/example-3-level.lab
example/simple-2-level.lab
example/simple.lab
htk_io/__init__.py
htk_io/alignment.py
htk_io/base.py
htk_io/hmgens_pdf.py
htk_io/misc.py
htk_io/ques.py
htk_io/test_alignment.py
htk_io/test_base.py
htk_io/tree.py
htk_io/vecseq.py
htk_io.egg-info/PKG-INFO
htk_io.egg-info/SOURCES.txt
htk_io.egg-info/dependency_links.txt
htk_io.egg-info/requires.txt
htk_io.egg-info/top_level.txt