Metadata-Version: 1.0
Name: htk-io
Version: 0.5
Summary: Read and write HTK and HTS files from python.
Home-page: http://github.com/MattShannon/htk_io
Author: Matt Shannon
Author-email: matt.shannon@cantab.net
License: 3-clause BSD (see License file)
Platform: UNKNOWN
